blueprint/__init__.py
blueprint/cli.py
blueprint/executor.py
blueprint/logging.py
blueprint/models.py
blueprint/parser.py
blueprint/scheduler.py
blueprint/validator.py
blueprint/generator/__init__.py
blueprint/generator/assembler.py
blueprint/generator/decomposer.py
blueprint/generator/interface_inferrer.py
blueprint/integrations/__init__.py
blueprint/integrations/aggregator.py
blueprint/integrations/outpost.py
blueprint/providers/__init__.py
blueprint/providers/anthropic.py
blueprint/providers/base.py
blueprint/providers/google.py
blueprint/providers/openai.py
blueprint/providers/outpost.py
blueprint/providers/registry.py
blueprint_ai-1.3.0.dist-info/METADATA
blueprint_ai-1.3.0.dist-info/WHEEL
blueprint_ai-1.3.0.dist-info/entry_points.txt
blueprint_ai-1.3.0.dist-info/RECORD
