Metadata-Version: 2.4
Name: blueprint-ai
Version: 1.3.0
Summary: Specification compiler for AI agent orchestration
Project-URL: Homepage, https://github.com/zeroechelon/blueprint
Project-URL: Repository, https://github.com/zeroechelon/blueprint
Project-URL: Documentation, https://github.com/zeroechelon/blueprint/blob/main/docs/BLUEPRINT_SPEC.md
Author-email: Richie Suarez <richie@zeroechelon.com>
License-Expression: Apache-2.0
Keywords: agents,ai,compiler,llm,multi-agent,orchestration,specification
Classifier: Development Status :: 5 - Production/Stable
Classifier: Intended Audience :: Developers
Classifier: License :: OSI Approved :: Apache Software License
Classifier: Programming Language :: Python :: 3.11
Classifier: Programming Language :: Python :: 3.12
Classifier: Topic :: Scientific/Engineering :: Artificial Intelligence
Classifier: Topic :: Software Development :: Code Generators
Requires-Python: >=3.11
Requires-Dist: pydantic>=2.0.0
Requires-Dist: pyyaml>=6.0
Requires-Dist: tenacity>=8.2.0
Provides-Extra: all-providers
Requires-Dist: anthropic>=0.18.0; extra == 'all-providers'
Requires-Dist: boto3>=1.34.0; extra == 'all-providers'
Requires-Dist: google-generativeai>=0.3.0; extra == 'all-providers'
Requires-Dist: openai>=1.0.0; extra == 'all-providers'
Provides-Extra: anthropic
Requires-Dist: anthropic>=0.18.0; extra == 'anthropic'
Provides-Extra: dev
Requires-Dist: mypy>=1.8.0; extra == 'dev'
Requires-Dist: pytest-asyncio>=0.21.0; extra == 'dev'
Requires-Dist: pytest-cov>=4.0; extra == 'dev'
Requires-Dist: pytest>=7.0; extra == 'dev'
Requires-Dist: ruff>=0.1.0; extra == 'dev'
Provides-Extra: google
Requires-Dist: google-generativeai>=0.3.0; extra == 'google'
Provides-Extra: llm
Requires-Dist: anthropic>=0.18.0; extra == 'llm'
Provides-Extra: openai
Requires-Dist: openai>=1.0.0; extra == 'openai'
Provides-Extra: outpost
Requires-Dist: boto3>=1.34.0; extra == 'outpost'
